aprl/__init__.py
aprl/appareil/__init__.py
aprl/experimental/__init__.py
aprl/experimental/depinject.py
aprl/experimental/dvcspec.py
aprl/experimental/multirun_example.py
aprl/part/__init__.py
aprl/utils/__init__.py
aprl/utils/run.py
aprl-2024.4.10.1731.dist-info/LICENSE
aprl-2024.4.10.1731.dist-info/METADATA
aprl-2024.4.10.1731.dist-info/WHEEL
aprl-2024.4.10.1731.dist-info/entry_points.txt
aprl-2024.4.10.1731.dist-info/top_level.txt
aprl-2024.4.10.1731.dist-info/RECORD
