Metadata-Version: 2.1
Name: aprl
Version: 2024.4.10.1731
Project-URL: Repository, https://github.com/quentinf00/aprl-core.git
License-File: LICENSE
Requires-Dist: hydra-zen
Requires-Dist: toolz
